falco_cli/__about__.py
falco_cli/__init__.py
falco_cli/__main__.py
falco_cli/checks.py
falco_cli/config.py
falco_cli/utils.py
falco_cli/commands/__init__.py
falco_cli/commands/htmx.py
falco_cli/commands/htmx_extension.py
falco_cli/commands/reset_migrations.py
falco_cli/commands/rm_migrations.py
falco_cli/commands/start_app.py
falco_cli/commands/start_project.py
falco_cli/commands/sync_dotenv.py
falco_cli/commands/update_project.py
falco_cli/commands/work.py
falco_cli/commands/crud/__init__.py
falco_cli/commands/crud/model_crud.py
falco_cli/commands/crud/utils.py
falco_cli/crud/html/create.html.jinja
falco_cli/crud/html/detail.html.jinja
falco_cli/crud/html/list.html.jinja
falco_cli/crud/html/update.html.jinja
falco_cli/crud/python/forms.py.jinja
falco_cli/crud/python/views.py.jinja
falco_cli-0.26.6.dist-info/METADATA
falco_cli-0.26.6.dist-info/WHEEL
falco_cli-0.26.6.dist-info/entry_points.txt
falco_cli-0.26.6.dist-info/licenses/LICENSE
falco_cli-0.26.6.dist-info/RECORD
