Metadata-Version: 2.3
Name: falco-cli
Version: 0.26.6
Summary: Enhance your Django developer experience: CLI and Guides for the Modern Developer.
Project-URL: Documentation, https://falco.oluwatobi.dev/
Project-URL: Homepage, https://falco.oluwatobi.dev/
Project-URL: Issues, https://github.com/tobi-de/falco/issues
Project-URL: Source, https://github.com/tobi-de/falco
Author-email: Tobi DEGNON <tobidegnon@proton.me>
License-Expression: MIT
License-File: LICENSE
Keywords: cookiecutter,django,project-template,python
Classifier: Development Status :: 4 - Beta
Classifier: Framework :: Django :: 4
Classifier: Framework :: Django :: 4.0
Classifier: Framework :: Django :: 4.1
Classifier: Framework :: Django :: 4.2
Classifier: Framework :: Django :: 5.0
Classifier: Intended Audience :: Developers
Classifier: Natural Language :: English
Classifier: Programming Language :: Python
Classifier: Programming Language :: Python :: 3 :: Only
Classifier: Programming Language :: Python :: 3.10
Classifier: Programming Language :: Python :: 3.11
Classifier: Programming Language :: Python :: 3.12
Classifier: Programming Language :: Python :: Implementation :: CPython
Classifier: Programming Language :: Python :: Implementation :: PyPy
Requires-Python: >=3.10
Requires-Dist: autoflake
Requires-Dist: black
Requires-Dist: cappa
Requires-Dist: cookiecutter
Requires-Dist: cruft
Requires-Dist: djlint
Requires-Dist: honcho
Requires-Dist: httpx
Requires-Dist: isort
Requires-Dist: parso
Requires-Dist: rich
Requires-Dist: tomlkit
Provides-Extra: hatch
Requires-Dist: hatch; extra == 'hatch'
Provides-Extra: just
Requires-Dist: just-bin; extra == 'just'
